centml/__init__.py
centml/cli/__init__.py
centml/cli/cluster.py
centml/cli/login.py
centml/cli/main.py
centml/compiler/__init__.py
centml/compiler/backend.py
centml/compiler/config.py
centml/compiler/main.py
centml/compiler/server.py
centml/compiler/server_compilation.py
centml/compiler/utils.py
centml/compiler/prediction/__init__.py
centml/compiler/prediction/backend.py
centml/compiler/prediction/kdtree.py
centml/compiler/prediction/metric.py
centml/compiler/prediction/profiler.py
centml/sdk/__init__.py
centml/sdk/api.py
centml/sdk/auth.py
centml/sdk/config.py
centml/sdk/utils/__init__.py
centml/sdk/utils/client_certs.py
centml-0.4.6.dist-info/licenses/LICENSE
tests/__init__.py
tests/conftest.py
tests/test_backend.py
tests/test_helpers.py
tests/test_server.py
centml-0.4.6.dist-info/METADATA
centml-0.4.6.dist-info/WHEEL
centml-0.4.6.dist-info/entry_points.txt
centml-0.4.6.dist-info/top_level.txt
centml-0.4.6.dist-info/RECORD
