Metadata-Version: 2.4
Name: centml
Version: 0.4.6
Requires-Python: >=3.10
License-File: LICENSE
Requires-Dist: fastapi>=0.103.0
Requires-Dist: uvicorn>=0.23.0
Requires-Dist: python-multipart>=0.0.6
Requires-Dist: pydantic-settings==2.0.*
Requires-Dist: Requests==2.32.2
Requires-Dist: tabulate>=0.9.0
Requires-Dist: pyjwt>=2.8.0
Requires-Dist: cryptography==44.0.1
Requires-Dist: prometheus-client>=0.20.0
Requires-Dist: scipy>=1.6.0
Requires-Dist: scikit-learn>=1.5.1
Requires-Dist: platform-api-python-client==4.1.9
Dynamic: description
Dynamic: description-content-type
Dynamic: license-file
Dynamic: requires-dist
Dynamic: requires-python
